MANIFEST.in
README.md
setup.cfg
setup.py
lehrex/VERSION
lehrex/__init__.py
lehrex/utils.py
lehrex.egg-info/PKG-INFO
lehrex.egg-info/SOURCES.txt
lehrex.egg-info/dependency_links.txt
lehrex.egg-info/requires.txt
lehrex.egg-info/top_level.txt
lehrex/csv/__init__.py
lehrex/csv/common.py
lehrex/csv/raw.py
lehrex/plots/__init__.py
lehrex/plots/common.py
lehrex/plots/plots.py