Metadata-Version: 1.1
Name: lehrex
Version: 1.1.1
Summary: Support the research during the Lehrexkursion.
Home-page: https://github.com/lkluft/lehrex
Author: Lukas Kluft
Author-email: lukas.kluft@gmail.com
License: MIT
Download-URL: https://github.com/lkluft/lehrex/tarball/v1.1.1
Platform: UNKNOWN
Classifier: Intended Audience :: Science/Research
Classifier: License :: OSI Approved :: MIT License
Classifier: Programming Language :: Python :: 3.5
Classifier: Programming Language :: Python :: 3.6
